odoo/addons/sale_stock_release_channel_partner_by_date/README.rst
odoo/addons/sale_stock_release_channel_partner_by_date/__init__.py
odoo/addons/sale_stock_release_channel_partner_by_date/__manifest__.py
odoo/addons/sale_stock_release_channel_partner_by_date/i18n/it.po
odoo/addons/sale_stock_release_channel_partner_by_date/i18n/sale_stock_release_channel_partner_by_date.pot
odoo/addons/sale_stock_release_channel_partner_by_date/models/__init__.py
odoo/addons/sale_stock_release_channel_partner_by_date/models/sale_order.py
odoo/addons/sale_stock_release_channel_partner_by_date/readme/CONTRIBUTORS.rst
odoo/addons/sale_stock_release_channel_partner_by_date/readme/DESCRIPTION.rst
odoo/addons/sale_stock_release_channel_partner_by_date/readme/USAGE.rst
odoo/addons/sale_stock_release_channel_partner_by_date/security/ir_model_access.xml
odoo/addons/sale_stock_release_channel_partner_by_date/static/description/icon.png
odoo/addons/sale_stock_release_channel_partner_by_date/static/description/index.html
odoo/addons/sale_stock_release_channel_partner_by_date/tests/__init__.py
odoo/addons/sale_stock_release_channel_partner_by_date/tests/common.py
odoo/addons/sale_stock_release_channel_partner_by_date/tests/test_sale_release_channel.py
odoo/addons/sale_stock_release_channel_partner_by_date/views/sale_order.xml
odoo_addon_sale_stock_release_channel_partner_by_date-16.0.1.1.0.2.dist-info/METADATA
odoo_addon_sale_stock_release_channel_partner_by_date-16.0.1.1.0.2.dist-info/WHEEL
odoo_addon_sale_stock_release_channel_partner_by_date-16.0.1.1.0.2.dist-info/top_level.txt
odoo_addon_sale_stock_release_channel_partner_by_date-16.0.1.1.0.2.dist-info/RECORD
